dosna/__init__.py
dosna/util/mpi.py
dosna/util/data.py
dosna/util/__init__.py
dosna/engines/jl.py
dosna/engines/base.py
dosna/engines/mpi.py
dosna/engines/__init__.py
dosna/engines/cpu.py
dosna/tests/__init__.py
dosna/tests/test_dataset.py
dosna/tests/test_connection.py
dosna/tests/test_dataset_mpi.py
dosna/backends/sage.py
dosna/backends/hdf5.py
dosna/backends/base.py
dosna/backends/__init__.py
dosna/backends/ceph.py
dosna/backends/ram.py
dosna/support/__init__.py
dosna/support/pyclovis/setup.py
dosna/support/pyclovis/__init__.py
dosna/support/pyclovis/test_pyclovis.py
dosna/support/pyclovis/simple_test.py
dosna/support/pyclovis/pyclovis.pyx
dosna/support/pyclovis/test_clovis_functions.c
dosna/support/pyclovis/clovis_functions.c
dosna/support/pyclovis/clovis_functions.h
dosna/support/pyclovis/clovis_test_config
dosna/support/pyclovis/pyclovis_test.conf
examples/backend_test.py
examples/convolution.py
examples/mpi_demo.py
examples/all_backends.py
examples/sequential_convolution.py
examples/__init__.py
examples/sort_chunks.py
examples/n-brute-n-body-simulation.py
DosNa-0.1.dist-info/top_level.txt
DosNa-0.1.dist-info/METADATA
DosNa-0.1.dist-info/DESCRIPTION.rst
DosNa-0.1.dist-info/metadata.json
DosNa-0.1.dist-info/WHEEL
DosNa-0.1.dist-info/RECORD
